deepseek/__init__.py
deepseek/helper.py
deepseek/main.py
deepseek/model.py
gemini/__init__.py
gemini/helper.py
gemini/main.py
gemini/model.py
hkatt/__init__.py
hkatt/main.py
htmltotext/__init__.py
htmltotext/main.py
ykatt/__init__.py
ykatt/main.py
deepseek_model-0.0.25.dist-info/METADATA
deepseek_model-0.0.25.dist-info/WHEEL
deepseek_model-0.0.25.dist-info/entry_points.txt
deepseek_model-0.0.25.dist-info/top_level.txt
deepseek_model-0.0.25.dist-info/RECORD
