Metadata-Version: 2.4
Name: deepseek-model
Version: 0.0.25
Requires-Dist: build
Requires-Dist: google-genai
Requires-Dist: groq
Requires-Dist: load_dotenv
Requires-Dist: markdownify
Requires-Dist: pymongo
Requires-Dist: pydantic
Requires-Dist: pyyaml
Requires-Dist: together
Requires-Dist: twine
Requires-Dist: PyYAML
